LICENSE
MANIFEST.in
README.rst
setup.py
completion/__init__.py
completion/constants.py
completion/listeners.py
completion/models.py
completion/sites.py
completion/urls.py
completion/utils.py
completion/views.py
completion/backends/__init__.py
completion/backends/base.py
completion/backends/db_backend.py
completion/backends/redis_backend.py
completion/backends/solr_backend.py
completion/completion_tests/__init__.py
completion/completion_tests/base.py
completion/completion_tests/db_backend.py
completion/completion_tests/models.py
completion/completion_tests/redis_backend.py
completion/completion_tests/site.py
completion/completion_tests/solr_backend.py
completion/completion_tests/tests.py
completion/completion_tests/utils.py
completion/fixtures/completion_testdata.json
completion/management/__init__.py
completion/management/commands/__init__.py
completion/management/commands/autocomplete_schema.py
completion/migrations/0001_initial.py
completion/migrations/__init__.py
completion/templates/completion/schema.xml.conf
django_completion.egg-info/PKG-INFO
django_completion.egg-info/SOURCES.txt
django_completion.egg-info/dependency_links.txt
django_completion.egg-info/not-zip-safe
django_completion.egg-info/top_level.txt